cefi/__init__.py
cefi/config.py
cefi/main.py
cefi/handler/__init__.py
cefi/handler/_client.py
cefi/handler/capitalcom.py
cefi/handler/ccxt.py
cefi/handler/ctrader.py
cefi/handler/degiro.py
cefi/handler/etoro.py
cefi/handler/etrade.py
cefi/handler/fixapi.py
cefi/handler/fxcm.py
cefi/handler/ibkr.py
cefi/handler/ig.py
cefi/handler/metatrader.py
cefi/handler/ninjatrader.py
cefi/handler/oanda.py
cefi/handler/schwab.py
cefi/handler/sierrachart.py
cefi/handler/thinkorswim.py
cefi/handler/tradestation.py
cefi/handler/tradingview.py
cefi-7.0.5.dist-info/licenses/LICENSE
cefi-7.0.5.dist-info/METADATA
cefi-7.0.5.dist-info/WHEEL
cefi-7.0.5.dist-info/top_level.txt
cefi-7.0.5.dist-info/RECORD
