Metadata-Version: 2.4
Name: cefi
Version: 7.0.5
Summary: A python library, to interact  with Crypto Exchanges (CCXT library) and brokers (IB & Capital.com)
Author-email: mraniki <8766259+mraniki@users.noreply.github.com>
License-Expression: MIT
Project-URL: Homepage, https://github.com/mraniki/cefi
Project-URL: Changelog, https://github.com/mraniki/cefi/blob/dev/CHANGELOG.rst
Project-URL: Support, https://github.com/mraniki/cefi/discussions
Project-URL: Issues, https://github.com/mraniki/cefi/issues
Keywords: cex, cefi, crypto, exchange, broker
Classifier: Programming Language :: Python :: 3
Classifier: Programming Language :: Python :: 3.10
Classifier: Programming Language :: Python :: 3.11
Classifier: Programming Language :: Python :: 3.12
Requires-Python: >=3.10
License-File: LICENSE
Requires-Dist: dynaconf>=3.1.12
Requires-Dist: loguru>=0.6
Requires-Dist: ccxt>=4.2.80
Requires-Dist: capitalcom-python==0.2.3
Requires-Dist: degiro-connector==3.0.29
Requires-Dist: easyoanda==1.0.19; python_version >= "3.11" and python_version < "4.0"
Requires-Dist: ibind==0.1.15
Requires-Dist: mt5linux_updated==0.0.1
Provides-Extra: dev
Requires-Dist: python-semantic-release>=8.0.8; extra == "dev"
Requires-Dist: ruff~=0.11; extra == "dev"
Requires-Dist: pre-commit~=4.0; extra == "dev"
Provides-Extra: test
Requires-Dist: pytest~=8.0; extra == "test"
Requires-Dist: pytest-cov~=6.0; extra == "test"
Requires-Dist: pytest-asyncio~=1.0; extra == "test"
Requires-Dist: pytest-mock~=3.11; extra == "test"
Requires-Dist: pytest-loguru~=0.4; extra == "test"
Provides-Extra: docs
Requires-Dist: sphinx==7.4.7; extra == "docs"
Requires-Dist: pydata-sphinx-theme~=0.14; extra == "docs"
Requires-Dist: sphinx-hoverxref~=1.3; extra == "docs"
Requires-Dist: sphinx_copybutton==0.5.2; extra == "docs"
Requires-Dist: myst_parser~=4.0; extra == "docs"
Requires-Dist: sphinx_design~=0.6; extra == "docs"
Dynamic: license-file
